{
    "data":[
        {
            "shdw":"福建六建集团有限公司",
            "gcmc":"巩义喜庆小镇一标段项目",
            "ht_num":"A20790",
            "sap_xszz":"1000",
            "sap_sdf":"400673",
            "sap_kh":"100390",
            "send_time":"2020-07-08",
            "station_name":"太龙",
            "business_man":"白嘉琪",
            "take_unit":"福建六建集团有限公司",
            "proj_name":"巩义喜庆小镇一标段项目",
            "jiaozhu_type":"地泵-10层以上",
            "proj_area":"11区5号楼14层墙柱梁板梯",
            "strong_lv":"C30",
            "goods_name":"混凝土",
            "weight_title":"河南省恒昌建材科技有限公司",
            "checi":2,
            "pinzhong":"",
            "yj_time":"60",
            "unit_price":"500",
            "send_count":"11.86",
            "fang":22.67,
            "ht_type":"合同",
            "sfkp":"开票",
            "startTime":"1594195109719",
            "arriveTime":"1594197001691",
            "returnTime":"0",
            "backTime":"0",
            "upperDistance":11862.230657866,
            "lowerDistance":0,
            "prod_phone":"15138960125",
            "sum_price":11335,
            "dist_price_ws":0,
            "dist_price_bf":0,
            "dist":"12"
        },
        {
            "shdw":"中电建路桥集团有限公司巩义分公司安庆市飞超实业有限公司",
            "gcmc":"巩义生态水系建设工程PPP一标段",
            "ht_num":"A20762",
            "sap_xszz":"1000",
            "sap_sdf":"400598",
            "sap_kh":"100327",
            "send_time":"2020-07-08",
            "station_name":"太龙",
            "business_man":"白嘉琪",
            "take_unit":"中电建路桥集团有限公司巩义分公司安庆市飞超实业有限公司",
            "proj_name":"巩义生态水系建设工程PPP一标段",
            "jiaozhu_type":"铲车端",
            "proj_area":"高速公路段服务区围墙墙板",
            "strong_lv":"C30",
            "goods_name":"混凝土",
            "weight_title":"河南省恒昌建材科技有限公司",
            "checi":1,
            "pinzhong":"",
            "yj_time":"90",
            "unit_price":"450",
            "send_count":"6.00",
            "fang":6,
            "ht_type":"预付款",
            "sfkp":"开票",
            "startTime":"1594193952564",
            "arriveTime":"1594194997161",
            "returnTime":"0",
            "backTime":"0",
            "upperDistance":17699.803515207,
            "lowerDistance":0,
            "prod_phone":"13805663238",
            "sum_price":2700,
            "dist_price_ws":0,
            "dist_price_bf":112,
            "dist":"8"
        },
        {
            "shdw":"河南久东建筑工程有限公司",
            "gcmc":"玫瑰雅苑",
            "ht_num":"A20729",
            "sap_xszz":"1000",
            "sap_sdf":"401114",
            "sap_kh":"100734",
            "send_time":"2020-07-08",
            "station_name":"太龙",
            "business_man":"孟新年",
            "take_unit":"河南久东建筑工程有限公司",
            "proj_name":"玫瑰雅苑",
            "jiaozhu_type":"地泵自备+10层以下",
            "proj_area":"桩基",
            "strong_lv":"C35",
            "goods_name":"混凝土",
            "weight_title":"河南省恒昌建材科技有限公司",
            "checi":3,
            "pinzhong":"",
            "yj_time":"60",
            "unit_price":"460",
            "send_count":"10.07",
            "fang":30.63,
            "ht_type":"预付款",
            "sfkp":"开票",
            "startTime":"1594189917345",
            "arriveTime":"1594191557691",
            "returnTime":"1594193826170",
            "backTime":"1594196771690",
            "upperDistance":9402.807595371,
            "lowerDistance":9427.4911082749,
            "prod_phone":"18625983709",
            "sum_price":14089.8,
            "dist_price_ws":0,
            "dist_price_bf":0,
            "dist":"10"
        },
        {
            "shdw":"兰立科",
            "gcmc":"兰立科",
            "ht_num":"A20797",
            "sap_xszz":"1000",
            "sap_sdf":"401147",
            "sap_kh":"100761",
            "send_time":"2020-07-08",
            "station_name":"山立",
            "business_man":"郑松绍",
            "take_unit":"兰立科",
            "proj_name":"兰立科",
            "jiaozhu_type":"铲车端",
            "proj_area":"芝田乡中地坪",
            "strong_lv":"C25",
            "goods_name":"混凝土",
            "weight_title":"河南省恒昌建材科技有限公司",
            "checi":1,
            "pinzhong":"",
            "yj_time":"90",
            "unit_price":"370",
            "send_count":"8.00",
            "fang":8,
            "ht_type":"预付款",
            "sfkp":"不要票",
            "startTime":"1594189838548",
            "arriveTime":"1594191660569",
            "returnTime":"1594194066764",
            "backTime":"1594195907972",
            "upperDistance":6596.4029076901,
            "lowerDistance":7059.7950042858,
            "prod_phone":"13938260165",
            "sum_price":2960,
            "dist_price_ws":0,
            "dist_price_bf":56,
            "dist":"15"
        },
        {
            "shdw":"中海华祥建设发展有限公司",
            "gcmc":"西村镇圣水村道路",
            "ht_num":"A20800",
            "sap_xszz":"2000",
            "sap_sdf":"401142",
            "sap_kh":"100757",
            "send_time":"2020-07-08",
            "station_name":"山立",
            "business_man":"白嘉琪",
            "take_unit":"中海华祥建设发展有限公司",
            "proj_name":"西村镇圣水村道路",
            "jiaozhu_type":"铲车端",
            "proj_area":"路面",
            "strong_lv":"C25",
            "goods_name":"混凝土",
            "weight_title":"河南省恒昌建材科技有限公司",
            "checi":3,
            "pinzhong":"",
            "yj_time":"90",
            "unit_price":"420",
            "send_count":"15.46",
            "fang":43.15,
            "ht_type":"预付款",
            "sfkp":"开票",
            "startTime":"1594186928702",
            "arriveTime":"1594193561778",
            "returnTime":"0",
            "backTime":"0",
            "upperDistance":40089.371675367,
            "lowerDistance":0,
            "prod_phone":"13803839498",
            "sum_price":18123,
            "dist_price_ws":0,
            "dist_price_bf":0,
            "dist":"15"
        },
        {
            "shdw":"福建六建集团有限公司",
            "gcmc":"巩义喜庆小镇一标段项目",
            "ht_num":"A20784",
            "sap_xszz":"1000",
            "sap_sdf":"400673",
            "sap_kh":"100390",
            "send_time":"2020-07-08",
            "station_name":"太龙",
            "business_man":"白嘉琪",
            "take_unit":"福建六建集团有限公司",
            "proj_name":"巩义喜庆小镇一标段项目",
            "jiaozhu_type":"塔吊",
            "proj_area":"8区3号楼38-56轴二构",
            "strong_lv":"C25",
            "goods_name":"混凝土",
            "weight_title":"河南省恒昌建材科技有限公司",
            "checi":1,
            "pinzhong":"细石",
            "yj_time":"120",
            "unit_price":"500",
            "send_count":"2.43",
            "fang":2.43,
            "ht_type":"合同",
            "sfkp":"开票",
            "startTime":"1594186178685",
            "arriveTime":"1594189304869",
            "returnTime":"1594193751540",
            "backTime":"1594196356251",
            "upperDistance":12407.173591751,
            "lowerDistance":12714.302969751,
            "prod_phone":"15516158829",
            "sum_price":1215,
            "dist_price_ws":0,
            "dist_price_bf":211.96,
            "dist":"12"
        },
        {
            "shdw":"安徽祥通建筑劳务有限公司",
            "gcmc":"巩义雅居乐喜庆小镇项目二标",
            "ht_num":"A20769",
            "sap_xszz":"1000",
            "sap_sdf":"400718",
            "sap_kh":"100420",
            "send_time":"2020-07-08",
            "station_name":"太龙",
            "business_man":"白嘉琪",
            "take_unit":"安徽祥通建筑劳务有限公司",
            "proj_name":"巩义雅居乐喜庆小镇项目二标",
            "jiaozhu_type":"地泵-10层以上",
            "proj_area":"6号楼24层墙柱梁板",
            "strong_lv":"C25",
            "goods_name":"混凝土",
            "weight_title":"河南省恒昌建材科技有限公司",
            "checi":5,
            "pinzhong":"",
            "yj_time":"60",
            "unit_price":"490",
            "send_count":"11.82",
            "fang":94.78,
            "ht_type":"合同",
            "sfkp":"开票",
            "startTime":"1594183841099",
            "arriveTime":"1594187557178",
            "returnTime":"1594188123101",
            "backTime":"1594189015773",
            "upperDistance":18321.215394631,
            "lowerDistance":13665.976754359,
            "prod_phone":"13177660182",
            "sum_price":46442.2,
            "dist_price_ws":0,
            "dist_price_bf":0,
            "dist":"12"
        },
        {
            "shdw":"安徽祥通建筑劳务有限公司",
            "gcmc":"巩义雅居乐喜庆小镇项目二标",
            "ht_num":"A20770",
            "sap_xszz":"1000",
            "sap_sdf":"400718",
            "sap_kh":"100420",
            "send_time":"2020-07-08",
            "station_name":"太龙",
            "business_man":"白嘉琪",
            "take_unit":"安徽祥通建筑劳务有限公司",
            "proj_name":"巩义雅居乐喜庆小镇项目二标",
            "jiaozhu_type":"地泵-10层以上",
            "proj_area":"6号楼24层",
            "strong_lv":"水",
            "goods_name":"原材料",
            "weight_title":"河南省恒昌建材科技有限公司",
            "checi":1,
            "pinzhong":"",
            "yj_time":"60",
            "unit_price":"300",
            "send_count":"6.90",
            "fang":6.9,
            "ht_type":"合同",
            "sfkp":"开票",
            "startTime":"1594183772939",
            "arriveTime":"1594185852599",
            "returnTime":"1594186617813",
            "backTime":"1594187453344",
            "upperDistance":14427.232070086,
            "lowerDistance":10517.828117662,
            "prod_phone":"13177660182",
            "sum_price":2070,
            "dist_price_ws":0,
            "dist_price_bf":0,
            "dist":"12"
        },
        {
            "shdw":"2020年巩义市鲁庄镇五顶坡村生产道路项目",
            "gcmc":"2020年巩义市鲁庄镇五顶坡村生产道路项目",
            "ht_num":"A20785",
            "sap_xszz":"1000",
            "sap_sdf":"401143",
            "sap_kh":"100758",
            "send_time":"2020-07-08",
            "station_name":"山立",
            "business_man":"郑松绍",
            "take_unit":"2020年巩义市鲁庄镇五顶坡村生产道路项目",
            "proj_name":"2020年巩义市鲁庄镇五顶坡村生产道路项目",
            "jiaozhu_type":"铲车端",
            "proj_area":"路面",
            "strong_lv":"C25",
            "goods_name":"混凝土",
            "weight_title":"河南省恒昌建材科技有限公司",
            "checi":5,
            "pinzhong":"",
            "yj_time":"90",
            "unit_price":"380",
            "send_count":"14.24",
            "fang":72.43,
            "ht_type":"预付款",
            "sfkp":"不要票",
            "startTime":"1594183991188",
            "arriveTime":"1594188806189",
            "returnTime":"1594190903083",
            "backTime":"1594195335203",
            "upperDistance":62575.68828561,
            "lowerDistance":56047.265902648,
            "prod_phone":"13838264147",
            "sum_price":27523.4,
            "dist_price_ws":0,
            "dist_price_bf":0,
            "dist":"30"
        },
        {
            "shdw":"河南联晟环保科技有限公司",
            "gcmc":"河南联晟环保科技有限公司",
            "ht_num":"A20791",
            "sap_xszz":"2000",
            "sap_sdf":"400505",
            "sap_kh":"100298",
            "send_time":"2020-07-08",
            "station_name":"山立",
            "business_man":"郑松绍",
            "take_unit":"河南联晟环保科技有限公司",
            "proj_name":"河南联晟环保科技有限公司",
            "jiaozhu_type":"塔吊",
            "proj_area":"地坪",
            "strong_lv":"C20",
            "goods_name":"混凝土",
            "weight_title":"河南省恒昌建材科技有限公司",
            "checi":2,
            "pinzhong":"",
            "yj_time":"120",
            "unit_price":"390",
            "send_count":"10.42",
            "fang":20.42,
            "ht_type":"预付款",
            "sfkp":"不要票",
            "startTime":"1594173271691",
            "arriveTime":"1594174547817",
            "returnTime":"1594180162128",
            "backTime":"1594181149024",
            "upperDistance":702.60260534802,
            "lowerDistance":810.41266822935,
            "prod_phone":"15617866588",
            "sum_price":7963.8,
            "dist_price_ws":0,
            "dist_price_bf":0,
            "dist":"5"
        },
        {
            "shdw":"韩成龙",
            "gcmc":"春天里二期",
            "ht_num":"A20774",
            "sap_xszz":"1000",
            "sap_sdf":"401087",
            "sap_kh":"100717",
            "send_time":"2020-07-08",
            "station_name":"山立",
            "business_man":"李新伟",
            "take_unit":"韩成龙",
            "proj_name":"春天里二期",
            "jiaozhu_type":"小车推",
            "proj_area":"车库地坪",
            "strong_lv":"C20",
            "goods_name":"混凝土",
            "weight_title":"河南省恒昌建材科技有限公司",
            "checi":2,
            "pinzhong":"",
            "yj_time":"90",
            "unit_price":"390",
            "send_count":"11.17",
            "fang":23.98,
            "ht_type":"预付款",
            "sfkp":"不要票",
            "startTime":"1594162742147",
            "arriveTime":"1594164331761",
            "returnTime":"1594169142167",
            "backTime":"1594170170794",
            "upperDistance":6664.4368285328,
            "lowerDistance":6883.2913776474,
            "prod_phone":"15981818587",
            "sum_price":9352.2,
            "dist_price_ws":60,
            "dist_price_bf":0,
            "dist":"12"
        },
        {
            "shdw":"兰立科",
            "gcmc":"兰立科",
            "ht_num":"A20772",
            "sap_xszz":"1000",
            "sap_sdf":"401147",
            "sap_kh":"100761",
            "send_time":"2020-07-08",
            "station_name":"太龙",
            "business_man":"郑松绍",
            "take_unit":"兰立科",
            "proj_name":"兰立科",
            "jiaozhu_type":"铲车端",
            "proj_area":"站街镇小黄冶村组道路路面",
            "strong_lv":"C25",
            "goods_name":"混凝土",
            "weight_title":"河南省恒昌建材科技有限公司",
            "checi":11,
            "pinzhong":"",
            "yj_time":"90",
            "unit_price":"370",
            "send_count":"14.22",
            "fang":161.61,
            "ht_type":"预付款",
            "sfkp":"不要票",
            "startTime":"1594162555016",
            "arriveTime":"1594166023669",
            "returnTime":"1594167095492",
            "backTime":"1594168589601",
            "upperDistance":74781.503851399,
            "lowerDistance":17875.04372352,
            "prod_phone":"15037196669",
            "sum_price":59795.7,
            "dist_price_ws":0,
            "dist_price_bf":0,
            "dist":"11"
        },
        {
            "shdw":"福建六建集团有限公司",
            "gcmc":"巩义喜庆小镇一标段项目",
            "ht_num":"A20778",
            "sap_xszz":"1000",
            "sap_sdf":"400673",
            "sap_kh":"100390",
            "send_time":"2020-07-08",
            "station_name":"太龙",
            "business_man":"白嘉琪",
            "take_unit":"福建六建集团有限公司",
            "proj_name":"巩义喜庆小镇一标段项目",
            "jiaozhu_type":"小车推",
            "proj_area":"6区11号楼16号楼",
            "strong_lv":"C25",
            "goods_name":"混凝土",
            "weight_title":"河南省恒昌建材科技有限公司",
            "checi":4,
            "pinzhong":"细石",
            "yj_time":"90",
            "unit_price":"500",
            "send_count":"5.05",
            "fang":20.48,
            "ht_type":"合同",
            "sfkp":"开票",
            "startTime":"1594162386643",
            "arriveTime":"1594166405487",
            "returnTime":"1594171562553",
            "backTime":"1594173475827",
            "upperDistance":10970.246545729,
            "lowerDistance":11050.258072329,
            "prod_phone":"18163855924",
            "sum_price":10240,
            "dist_price_ws":0,
            "dist_price_bf":546.56,
            "dist":"12"
        },
        {
            "shdw":"福建六建集团有限公司",
            "gcmc":"巩义喜庆小镇一标段项目",
            "ht_num":"A20764",
            "sap_xszz":"1000",
            "sap_sdf":"400673",
            "sap_kh":"100390",
            "send_time":"2020-07-08",
            "station_name":"太龙",
            "business_man":"白嘉琪",
            "take_unit":"福建六建集团有限公司",
            "proj_name":"巩义喜庆小镇一标段项目",
            "jiaozhu_type":"小车推",
            "proj_area":"6区7号楼4层构造柱",
            "strong_lv":"C20",
            "goods_name":"混凝土",
            "weight_title":"河南省恒昌建材科技有限公司",
            "checi":2,
            "pinzhong":"细石",
            "yj_time":"90",
            "unit_price":"490",
            "send_count":"3.58",
            "fang":7.23,
            "ht_type":"合同",
            "sfkp":"开票",
            "startTime":"1594159467654",
            "arriveTime":"1594161510584",
            "returnTime":"1594174312509",
            "backTime":"1594176347127",
            "upperDistance":2968.5865639849,
            "lowerDistance":11049.464821106,
            "prod_phone":"13014512293",
            "sum_price":3542.7,
            "dist_price_ws":369,
            "dist_price_bf":357.56,
            "dist":"12"
        },
        {
            "shdw":"巩义市银山冶金材料有限公司",
            "gcmc":"设备基础",
            "ht_num":"A20771",
            "sap_xszz":"1000",
            "sap_sdf":"401150",
            "sap_kh":"100762",
            "send_time":"2020-07-08",
            "station_name":"山立",
            "business_man":"连志伟",
            "take_unit":"巩义市银山冶金材料有限公司",
            "proj_name":"设备基础",
            "jiaozhu_type":"自卸",
            "proj_area":"设备基础",
            "strong_lv":"C40",
            "goods_name":"混凝土",
            "weight_title":"河南省恒昌建材科技有限公司",
            "checi":5,
            "pinzhong":"",
            "yj_time":"60",
            "unit_price":"460",
            "send_count":"13.29",
            "fang":65,
            "ht_type":"预付款",
            "sfkp":"开票",
            "startTime":"1594158071044",
            "arriveTime":"1594160478300",
            "returnTime":"1594161764492",
            "backTime":"1594163429318",
            "upperDistance":9589.7578963959,
            "lowerDistance":9598.937006348,
            "prod_phone":"13938273369",
            "sum_price":29900,
            "dist_price_ws":0,
            "dist_price_bf":0,
            "dist":"15"
        },
        {
            "shdw":"2020年巩义市鲁庄镇五顶坡村生产道路项目",
            "gcmc":"2020年巩义市鲁庄镇五顶坡村生产道路项目",
            "ht_num":"A20777",
            "sap_xszz":"1000",
            "sap_sdf":"401143",
            "sap_kh":"100758",
            "send_time":"2020-07-08",
            "station_name":"山立",
            "business_man":"郑松绍",
            "take_unit":"2020年巩义市鲁庄镇五顶坡村生产道路项目",
            "proj_name":"2020年巩义市鲁庄镇五顶坡村生产道路项目",
            "jiaozhu_type":"铲车端",
            "proj_area":"路面",
            "strong_lv":"C25",
            "goods_name":"混凝土",
            "weight_title":"河南省恒昌建材科技有限公司",
            "checi":6,
            "pinzhong":"",
            "yj_time":"90",
            "unit_price":"380",
            "send_count":"14.46",
            "fang":86.29,
            "ht_type":"预付款",
            "sfkp":"不要票",
            "startTime":"1594154908323",
            "arriveTime":"1594159654528",
            "returnTime":"1594160100762",
            "backTime":"1594163601283",
            "upperDistance":45483.724499122,
            "lowerDistance":49072.153592444,
            "prod_phone":"13838264147",
            "sum_price":32790.2,
            "dist_price_ws":0,
            "dist_price_bf":0,
            "dist":"30"
        },
        {
            "shdw":"张建超",
            "gcmc":"张建超",
            "ht_num":"A20773",
            "sap_xszz":"1000",
            "sap_sdf":"401127",
            "sap_kh":"100744",
            "send_time":"2020-07-08",
            "station_name":"山立",
            "business_man":"郑松绍",
            "take_unit":"张建超",
            "proj_name":"张建超",
            "jiaozhu_type":"铲车端",
            "proj_area":"鲁庄镇外河村道路路面",
            "strong_lv":"C25",
            "goods_name":"混凝土",
            "weight_title":"河南省恒昌建材科技有限公司",
            "checi":5,
            "pinzhong":"",
            "yj_time":"90",
            "unit_price":"380",
            "send_count":"12.14",
            "fang":63.01,
            "ht_type":"预付款",
            "sfkp":"不要票",
            "startTime":"1594154529395",
            "arriveTime":"1594159911374",
            "returnTime":"1594163425446",
            "backTime":"1594167966853",
            "upperDistance":27348.840871025,
            "lowerDistance":27300.709774484,
            "prod_phone":"18339913686",
            "sum_price":23943.8,
            "dist_price_ws":0,
            "dist_price_bf":0,
            "dist":"31"
        }
    ],
    "code":0,
    "msg":"",
    "start":"2020-07-08 00:00:00",
    "end":"2020-07-08 16:33:50",
    "count":35
}