{
	"code": 0,
	"data": [{
		"ht_num": "A19991",
		"take_unit": "中铁七局集团郑州工程有限公司",
		"proj_name": "康芝路项目",
		"proj_area": "5770到5830中分带左侧路缘石靠背",
		"all_count": "6",
		"strong_lv": "C15",
		"tanluo_lv": "200",
		"jiaozhu_type": "自卸",
		"kangshen_lv": "",
		"zhefang_ratio": "",
		"zhefang_use": "方",
		"use_status": "完工",
		"recv_status": "",
		"create_time": "2020-06-22 14:56:46",
		"proj_addr": "康芝路益家窝大桥向北100米",
		"use_time": null,
		"use_count": 1,
		"business_man": "李元博",
		"ht_type": "合同",
		"pb_num": "",
		"trans_dist": "15",
		"start_time": "2020-06-22 15:54:00",
		"prod_phone": "18638702706",
		"create_man": "生产技术控制中心",
		"station_name": "恒昌站",
		"conn_man": "郑松涛",
		"pack_type": "",
		"weight_title": "河南省恒昌建材科技有限公司",
		"zdbz": "",
		"beizhu": null,
		"goods_name": "混凝土",
		"sap_num": "0040016545",
		"phb_num": "SX15-005",
		"price": "439",
		"yj_time": "60",
		"dcbc_price": "",
		"cgbf_price": "",
		"sgbc": " ",
		"pinzhong": "细石",
		"sfkp": "开票",
		"yw_price": "20",
		"gs_code": "1000",
		"kh_num": "100042",
		"sdf_num": "400121",
		"wuliao": "1000006591",
		"trans_type": "供应商承运",
		"pord_info": "C15\/新安\/人工细石\/SX15-005",
		"ys_standrd": "受检",
		"gd_data": "要资料",
		"sap_statuss": "E",
		"rg_phb_num": "",
		"rg_wuliao_num": "",
		"rg_pord_info": "",
		"khmc": ""
	}, {
		"ht_num": "A19990",
		"take_unit": "中电建路桥集团有限公司巩义分公司安庆市飞超实业有限公司",
		"proj_name": "巩义生态水系建设工程PPP一标段",
		"proj_area": "排水管护管",
		"all_count": "20",
		"strong_lv": "C20",
		"tanluo_lv": "200",
		"jiaozhu_type": "铲车端",
		"kangshen_lv": "",
		"zhefang_ratio": "",
		"zhefang_use": "方",
		"use_status": "完工",
		"recv_status": "",
		"create_time": "2020-06-22 14:41:58",
		"proj_addr": "站街苍西上山路厕所旁老路",
		"use_time": null,
		"use_count": 2,
		"business_man": "白嘉琪",
		"ht_type": "预付款",
		"pb_num": "",
		"trans_dist": "5",
		"start_time": "2020-06-22 15:30:00",
		"prod_phone": "13723201927",
		"create_man": "生产技术控制中心",
		"station_name": "恒昌站",
		"conn_man": "王工",
		"pack_type": "",
		"weight_title": "河南省恒昌建材科技有限公司",
		"zdbz": "",
		"beizhu": "带随车资料。",
		"goods_name": "混凝土",
		"sap_num": "0040016542",
		"phb_num": "SX20-007",
		"price": "430",
		"yj_time": "90",
		"dcbc_price": "",
		"cgbf_price": "",
		"sgbc": " ",
		"pinzhong": "",
		"sfkp": "开票",
		"yw_price": "",
		"gs_code": "1000",
		"kh_num": "100327",
		"sdf_num": "400598",
		"wuliao": "1000006605",
		"trans_type": "供应商承运",
		"pord_info": "C20\/新安\/人工基础\/SX20-007",
		"ys_standrd": "受检",
		"gd_data": "要资料",
		"sap_statuss": "S",
		"rg_phb_num": "",
		"rg_wuliao_num": "",
		"rg_pord_info": "",
		"khmc": ""
	}, {
		"ht_num": "A19989",
		"take_unit": "河南盛之佳建材有限公司巩义建业春天里4.5期",
		"proj_name": "中建七局第四建筑有限公司巩义建业春天里4.5期",
		"proj_area": "3号楼4层卫生间挡水台",
		"all_count": "4",
		"strong_lv": "C25",
		"tanluo_lv": "220",
		"jiaozhu_type": "小车推",
		"kangshen_lv": "",
		"zhefang_ratio": "",
		"zhefang_use": "方",
		"use_status": "完工",
		"recv_status": "",
		"create_time": "2020-06-22 11:37:43",
		"proj_addr": "建业春天里五期",
		"use_time": null,
		"use_count": 1,
		"business_man": "连志伟",
		"ht_type": "预付款",
		"pb_num": "",
		"trans_dist": "10",
		"start_time": "2020-06-22 13:30:00",
		"prod_phone": "18695885822",
		"create_man": "生产技术控制中心",
		"station_name": "山立站",
		"conn_man": "任东",
		"pack_type": "",
		"weight_title": "河南省恒昌建材科技有限公司",
		"zdbz": "",
		"beizhu": null,
		"goods_name": "混凝土",
		"sap_num": "0040016535",
		"phb_num": "SX25-011",
		"price": "420",
		"yj_time": "90",
		"dcbc_price": "",
		"cgbf_price": "",
		"sgbc": " ",
		"pinzhong": "",
		"sfkp": "开票",
		"yw_price": "",
		"gs_code": "1000",
		"kh_num": "100703",
		"sdf_num": "401076",
		"wuliao": "1000006632",
		"trans_type": "供应商承运",
		"pord_info": "C25\/新安\/人工结构\/SX25-011",
		"ys_standrd": "受检",
		"gd_data": "要资料",
		"sap_statuss": "S",
		"rg_phb_num": "",
		"rg_wuliao_num": "",
		"rg_pord_info": "",
		"khmc": ""
	}, {
		"ht_num": "A19988",
		"take_unit": "河南盛之佳建材有限公司巩义建业春天里2.3期",
		"proj_name": "中建七局第四建筑有限公司巩义建业春天里2.3期",
		"proj_area": "三期8号楼屋面找平层",
		"all_count": "16",
		"strong_lv": "M10湿拌",
		"tanluo_lv": "220",
		"jiaozhu_type": "塔吊",
		"kangshen_lv": "",
		"zhefang_ratio": "",
		"zhefang_use": "方",
		"use_status": "完工",
		"recv_status": "",
		"create_time": "2020-06-22 11:14:50",
		"proj_addr": "三期西门",
		"use_time": null,
		"use_count": 2,
		"business_man": "连志伟",
		"ht_type": "预付款",
		"pb_num": "",
		"trans_dist": "10",
		"start_time": "2020-06-22 13:16:00",
		"prod_phone": "15378727506",
		"create_man": "生产技术控制中心",
		"station_name": "山立站",
		"conn_man": "王振",
		"pack_type": "",
		"weight_title": "河南省恒昌建材科技有限公司",
		"zdbz": "",
		"beizhu": null,
		"goods_name": "湿拌砂浆",
		"sap_num": "0040016539",
		"phb_num": "P50-44",
		"price": "390",
		"yj_time": "120",
		"dcbc_price": "",
		"cgbf_price": "",
		"sgbc": " ",
		"pinzhong": "",
		"sfkp": "开票",
		"yw_price": "",
		"gs_code": "1000",
		"kh_num": "100650",
		"sdf_num": "401011",
		"wuliao": "1000001400",
		"trans_type": "供应商承运",
		"pord_info": "M10\/地坪\/湿拌砂浆\/P50-44",
		"ys_standrd": "受检",
		"gd_data": "要资料",
		"sap_statuss": "S",
		"rg_phb_num": "",
		"rg_wuliao_num": "",
		"rg_pord_info": "",
		"khmc": ""
	}, {
		"ht_num": "A19986",
		"take_unit": "郑州铁路工程有限公司巩义市康芝路黑石关铁路箱涵项目",
		"proj_name": "巩义市康芝路黑石关铁路箱涵项目",
		"proj_area": "挡墙垫层",
		"all_count": "8",
		"strong_lv": "C20",
		"tanluo_lv": "220",
		"jiaozhu_type": "人工",
		"kangshen_lv": "",
		"zhefang_ratio": "",
		"zhefang_use": "方",
		"use_status": "完工",
		"recv_status": "",
		"create_time": "2020-06-22 10:52:46",
		"proj_addr": "东黑石关村",
		"use_time": null,
		"use_count": 1,
		"business_man": "白嘉琪",
		"ht_type": "合同",
		"pb_num": "",
		"trans_dist": "10",
		"start_time": "2020-06-22 14:50:00",
		"prod_phone": "13393747374",
		"create_man": "生产技术控制中心",
		"station_name": "山立站",
		"conn_man": "李登辉",
		"pack_type": "",
		"weight_title": "河南省恒昌建材科技有限公司",
		"zdbz": "",
		"beizhu": null,
		"goods_name": "混凝土",
		"sap_num": "0040016546",
		"phb_num": "SS20-010",
		"price": "450",
		"yj_time": "60",
		"dcbc_price": "",
		"cgbf_price": "",
		"sgbc": " ",
		"pinzhong": "",
		"sfkp": "开票",
		"yw_price": "",
		"gs_code": "1000",
		"kh_num": "100521",
		"sdf_num": "400863",
		"wuliao": "1000006761",
		"trans_type": "供应商承运",
		"pord_info": "C20\/嵩基\/人工垫层\/SS20-010",
		"ys_standrd": "受检",
		"gd_data": "要资料",
		"sap_statuss": "S",
		"rg_phb_num": "",
		"rg_wuliao_num": "",
		"rg_pord_info": "",
		"khmc": ""
	}, {
		"ht_num": "A19985",
		"take_unit": "河南盛之佳建材有限公司巩义建业春天里2.3期",
		"proj_name": "中建七局第四建筑有限公司巩义建业春天里2.3期",
		"proj_area": "13号楼北侧裙楼基础",
		"all_count": "7",
		"strong_lv": "C15",
		"tanluo_lv": "220",
		"jiaozhu_type": "塔吊",
		"kangshen_lv": "",
		"zhefang_ratio": "",
		"zhefang_use": "方",
		"use_status": "完工",
		"recv_status": "",
		"create_time": "2020-06-22 10:48:06",
		"proj_addr": "三期",
		"use_time": null,
		"use_count": 1,
		"business_man": "连志伟",
		"ht_type": "预付款",
		"pb_num": "",
		"trans_dist": "20",
		"start_time": "2020-06-22 13:50:00",
		"prod_phone": "17719996606",
		"create_man": "生产技术控制中心",
		"station_name": "山立站",
		"conn_man": "孙胜权",
		"pack_type": "",
		"weight_title": "河南省恒昌建材科技有限公司",
		"zdbz": "",
		"beizhu": null,
		"goods_name": "混凝土",
		"sap_num": "0040016536",
		"phb_num": "SX15-005",
		"price": "400",
		"yj_time": "120",
		"dcbc_price": "",
		"cgbf_price": "",
		"sgbc": " ",
		"pinzhong": "细石",
		"sfkp": "开票",
		"yw_price": "",
		"gs_code": "1000",
		"kh_num": "100650",
		"sdf_num": "401011",
		"wuliao": "1000006591",
		"trans_type": "供应商承运",
		"pord_info": "C15\/新安\/人工细石\/SX15-005",
		"ys_standrd": "受检",
		"gd_data": "要资料",
		"sap_statuss": "S",
		"rg_phb_num": "",
		"rg_wuliao_num": "",
		"rg_pord_info": "",
		"khmc": ""
	}, {
		"ht_num": "A19979",
		"take_unit": "郑州银河建筑工程有限公司工程服务分公司",
		"proj_name": "公司基建恒昌站",
		"proj_area": "太龙站电子公司厂区改造地磅基础",
		"all_count": "20",
		"strong_lv": "C30",
		"tanluo_lv": "200",
		"jiaozhu_type": "自卸",
		"kangshen_lv": "",
		"zhefang_ratio": "",
		"zhefang_use": "方",
		"use_status": "完工",
		"recv_status": "",
		"create_time": "2020-06-22 09:49:56",
		"proj_addr": "电子公司",
		"use_time": null,
		"use_count": 1,
		"business_man": "王泽辉",
		"ht_type": "关联客户",
		"pb_num": "",
		"trans_dist": "2",
		"start_time": "2020-06-22 14:31:00",
		"prod_phone": "15516951557",
		"create_man": "生产技术控制中心",
		"station_name": "恒昌站",
		"conn_man": "赵国强",
		"pack_type": "",
		"weight_title": "河南省恒昌建材科技有限公司",
		"zdbz": "",
		"beizhu": null,
		"goods_name": "混凝土",
		"sap_num": "0040016538",
		"phb_num": "SX30-019",
		"price": "460",
		"yj_time": "60",
		"dcbc_price": "",
		"cgbf_price": "",
		"sgbc": " ",
		"pinzhong": "",
		"sfkp": "开票",
		"yw_price": "",
		"gs_code": "1000",
		"kh_num": "3000",
		"sdf_num": "400236",
		"wuliao": "1000006665",
		"trans_type": "供应商承运",
		"pord_info": "C30\/新安\/人工基础\/SX30-019",
		"ys_standrd": "受检",
		"gd_data": "要资料",
		"sap_statuss": "S",
		"rg_phb_num": "",
		"rg_wuliao_num": "",
		"rg_pord_info": "",
		"khmc": ""
	}, {
		"ht_num": "A19978",
		"take_unit": "福建六建集团有限公司",
		"proj_name": "巩义喜庆小镇一标段项目",
		"proj_area": "6区11号楼4层止水反坎",
		"all_count": "6",
		"strong_lv": "C20",
		"tanluo_lv": "220",
		"jiaozhu_type": "小车推",
		"kangshen_lv": "",
		"zhefang_ratio": "",
		"zhefang_use": "方",
		"use_status": "完工",
		"recv_status": "",
		"create_time": "2020-06-22 09:34:41",
		"proj_addr": "6区11号楼4层",
		"use_time": null,
		"use_count": 1,
		"business_man": "白嘉琪",
		"ht_type": "合同",
		"pb_num": "",
		"trans_dist": "15",
		"start_time": "2020-06-22 13:15:00",
		"prod_phone": "19937105355",
		"create_man": "生产技术控制中心",
		"station_name": "恒昌站",
		"conn_man": "吴迎亚",
		"pack_type": "",
		"weight_title": "河南省恒昌建材科技有限公司",
		"zdbz": "",
		"beizhu": "小门进，等电话",
		"goods_name": "混凝土",
		"sap_num": "0040016537",
		"phb_num": "SX20-012",
		"price": "490",
		"yj_time": "90",
		"dcbc_price": "",
		"cgbf_price": "",
		"sgbc": " ",
		"pinzhong": "细石",
		"sfkp": "开票",
		"yw_price": "",
		"gs_code": "1000",
		"kh_num": "100390",
		"sdf_num": "400673",
		"wuliao": "1000006610",
		"trans_type": "供应商承运",
		"pord_info": "C20\/新安\/人工细石\/SX20-012",
		"ys_standrd": "受检",
		"gd_data": "要资料",
		"sap_statuss": "S",
		"rg_phb_num": "",
		"rg_wuliao_num": "",
		"rg_pord_info": "",
		"khmc": ""
	}, {
		"ht_num": "A19974",
		"take_unit": "福建六建集团有限公司",
		"proj_name": "巩义喜庆小镇一标段项目",
		"proj_area": "11区4号楼7层墙柱",
		"all_count": "90",
		"strong_lv": "C40",
		"tanluo_lv": "210",
		"jiaozhu_type": "地泵-10层以上",
		"kangshen_lv": "",
		"zhefang_ratio": "",
		"zhefang_use": "方",
		"use_status": "完工",
		"recv_status": "",
		"create_time": "2020-06-22 08:42:00",
		"proj_addr": "雅居乐11区4号楼7层",
		"use_time": null,
		"use_count": 0,
		"business_man": "白嘉琪",
		"ht_type": "合同",
		"pb_num": "",
		"trans_dist": "10",
		"start_time": "2020-06-22 20:20:00",
		"prod_phone": "15093663920",
		"create_man": "生产技术控制中心",
		"station_name": "恒昌站",
		"conn_man": "陈亮",
		"pack_type": "",
		"weight_title": "河南省恒昌建材科技有限公司",
		"zdbz": "",
		"beizhu": "",
		"goods_name": "混凝土",
		"sap_num": "",
		"phb_num": "SY40-008",
		"price": "530",
		"yj_time": "60",
		"dcbc_price": "",
		"cgbf_price": "",
		"sgbc": " ",
		"pinzhong": "",
		"sfkp": "开票",
		"yw_price": "",
		"gs_code": "1000",
		"kh_num": "100390",
		"sdf_num": "400673",
		"wuliao": "1000006561",
		"trans_type": "供应商承运",
		"pord_info": "C40\/永安\/主体结构\/SY40-008",
		"ys_standrd": "受检",
		"gd_data": "要资料",
		"sap_statuss": "",
		"rg_phb_num": "R-01",
		"rg_wuliao_num": "1000001675",
		"rg_pord_info": "润管砂浆\/R-01",
		"khmc": ""
	}, {
		"ht_num": "A19973",
		"take_unit": "福建六建集团有限公司",
		"proj_name": "巩义喜庆小镇一标段项目",
		"proj_area": "11区4号楼7层梁板梯",
		"all_count": "56",
		"strong_lv": "C30",
		"tanluo_lv": "210",
		"jiaozhu_type": "地泵-10层以上",
		"kangshen_lv": "",
		"zhefang_ratio": "",
		"zhefang_use": "方",
		"use_status": "完工",
		"recv_status": "",
		"create_time": "2020-06-22 08:38:47",
		"proj_addr": "雅居乐11区4号楼7层",
		"use_time": null,
		"use_count": 0,
		"business_man": "白嘉琪",
		"ht_type": "合同",
		"pb_num": "",
		"trans_dist": "10",
		"start_time": "2020-06-22 20:20:00",
		"prod_phone": "15093663920",
		"create_man": "生产技术控制中心",
		"station_name": "恒昌站",
		"conn_man": "陈亮",
		"pack_type": "",
		"weight_title": "河南省恒昌建材科技有限公司",
		"zdbz": "",
		"beizhu": "",
		"goods_name": "混凝土",
		"sap_num": "",
		"phb_num": "SY30-011",
		"price": "500",
		"yj_time": "60",
		"dcbc_price": "",
		"cgbf_price": "",
		"sgbc": " ",
		"pinzhong": "",
		"sfkp": "开票",
		"yw_price": "",
		"gs_code": "1000",
		"kh_num": "100390",
		"sdf_num": "400673",
		"wuliao": "1000006504",
		"trans_type": "供应商承运",
		"pord_info": "C30\/永安\/泵送主体1-10层\/SY30-011",
		"ys_standrd": "受检",
		"gd_data": "要资料",
		"sap_statuss": "",
		"rg_phb_num": "R-01",
		"rg_wuliao_num": "1000001675",
		"rg_pord_info": "润管砂浆\/R-01",
		"khmc": ""
	}],
	"count": 23523
}