{
    "code": 0,
    "count":32,
    "data": [
        {
            "accoun": "郑会娟",
            "com_code": "1000",
            "com_code_short": "恒昌建材|1000",
            "comment": "",
            "create_time": "2020-06-19",
            "exec_time": "2020-06-19 15:24:06",
            "grant_unit": "7000",
            "grant_unit_short": "资金事业部|7000",
            "grant_way": "现金",
            "initiatorr": "李利涓",
            "initiatorr_c": "",
            "into_accounts_caty": null,
            "into_accounts_desc": null,
            "into_accounts_short": null,
            "into_shoft": null,
            "money_b": "陆仟元整",
            "money_center": "",
            "money_l": "6000",
            "promise_num": null,
            "purpose": "恒昌建材承担刘红章集资款利息6000元（刘红章恒昌原始股东）",
            "real_time": "2020-06-19 14:51:17",
            "sap_back": "910000176710002020/910000030970002020",
            "sap_msg": "会计凭证创建成功",
            "sap_status": "S",
            "sap_time": "2020-06-19 15:24:00",
            "sap_user": "HC0131",
            "serial_num": "616927",
            "shift_accounts_caty": null,
            "shift_accounts_desc": null,
            "shift_accounts_short": null,
            "shift_short": "",
            "submitter": "郑会娟"
        },
        {
            "accoun": "郑会娟",
            "com_code": "7000",
            "com_code_short": "资金事业部|7000",
            "comment": "",
            "create_time": "2020-06-19",
            "exec_time": "2020-06-19 14:41:53",
            "grant_unit": "2000",
            "grant_unit_short": "山立建材|2000",
            "grant_way": "现金",
            "initiatorr": "李利涓",
            "initiatorr_c": "",
            "into_accounts_caty": null,
            "into_accounts_desc": null,
            "into_accounts_short": null,
            "into_shoft": null,
            "money_b": "壹拾玖万零捌佰玖拾肆元肆角玖分",
            "money_center": "",
            "money_l": "190894.49",
            "promise_num": null,
            "purpose": "资金部付山立郑松邵承担的垫支利息款",
            "real_time": "2020-06-19 14:34:12",
            "sap_back": "910000030870002020/910000088320002020",
            "sap_msg": "会计凭证创建成功",
            "sap_status": "S",
            "sap_time": "2020-06-19 14:41:47",
            "sap_user": "HC0131",
            "serial_num": "616916",
            "shift_accounts_caty": null,
            "shift_accounts_desc": null,
            "shift_accounts_short": null,
            "shift_short": "",
            "submitter": "郑会娟"
        },
        {
            "accoun": "连娟",
            "com_code": "7000",
            "com_code_short": "资金事业部|7000",
            "comment": "",
            "create_time": "2020-06-19",
            "exec_time": "2020-06-19 14:39:58",
            "grant_unit": "8000",
            "grant_unit_short": "行政事业部|8000",
            "grant_way": "现金",
            "initiatorr": "李利涓",
            "initiatorr_c": "",
            "into_accounts_caty": null,
            "into_accounts_desc": null,
            "into_accounts_short": null,
            "into_shoft": null,
            "money_b": "叁佰伍拾柒元贰角",
            "money_center": "",
            "money_l": "357.2",
            "promise_num": null,
            "purpose": "资金部付吴智涛承担车辆767商业险357.2",
            "real_time": "2020-06-19 14:25:49",
            "sap_back": "910000030770002020/910000027580002020",
            "sap_msg": "会计凭证创建成功",
            "sap_status": "S",
            "sap_time": "2020-06-19 14:39:52",
            "sap_user": "HC0121",
            "serial_num": "616915",
            "shift_accounts_caty": null,
            "shift_accounts_desc": null,
            "shift_accounts_short": null,
            "shift_short": "",
            "submitter": "连娟"
        },
        {
            "accoun": "连娟",
            "com_code": "7000",
            "com_code_short": "资金事业部|7000",
            "comment": "",
            "create_time": "2020-06-19",
            "exec_time": "2020-06-19 14:24:39",
            "grant_unit": "8000",
            "grant_unit_short": "行政事业部|8000",
            "grant_way": "现金",
            "initiatorr": "李利涓",
            "initiatorr_c": "",
            "into_accounts_caty": null,
            "into_accounts_desc": null,
            "into_accounts_short": null,
            "into_shoft": null,
            "money_b": "壹仟元整",
            "money_center": "",
            "money_l": "1000",
            "promise_num": null,
            "purpose": "资金部付行政郭建平罚款",
            "real_time": "2020-06-19 14:20:11",
            "sap_back": "910000030670002020/910000027480002020",
            "sap_msg": "会计凭证创建成功",
            "sap_status": "S",
            "sap_time": "2020-06-19 14:24:33",
            "sap_user": "HC0121",
            "serial_num": "616914",
            "shift_accounts_caty": null,
            "shift_accounts_desc": null,
            "shift_accounts_short": null,
            "shift_short": "",
            "submitter": "连娟"
        },
        {
            "accoun": "李利涓",
            "com_code": "7000",
            "com_code_short": "资金事业部|7000",
            "comment": "",
            "create_time": "2020-06-18",
            "exec_time": "2020-06-18 15:33:44",
            "grant_unit": "1000",
            "grant_unit_short": "恒昌建材|1000",
            "grant_way": "现金",
            "initiatorr": "郑会娟",
            "initiatorr_c": "",
            "into_accounts_caty": null,
            "into_accounts_desc": null,
            "into_accounts_short": null,
            "into_shoft": null,
            "money_b": "叁万伍仟元整",
            "money_center": "",
            "money_l": "35000",
            "promise_num": null,
            "purpose": "518079#8万上规模企业费用，有资金部记账。598236#收社保局45000元属于资金部退回",
            "real_time": "2020-06-18 15:29:29",
            "sap_back": "910000030370002020/910000175910002020",
            "sap_msg": "会计凭证创建成功",
            "sap_status": "S",
            "sap_time": "2020-06-18 15:33:38",
            "sap_user": "HC0120",
            "serial_num": "616195",
            "shift_accounts_caty": null,
            "shift_accounts_desc": null,
            "shift_accounts_short": null,
            "shift_short": "",
            "submitter": "李利涓"
        },
        {
            "accoun": "张昕",
            "com_code": "1000",
            "com_code_short": "恒昌建材|1000",
            "comment": "",
            "create_time": "2020-06-17",
            "exec_time": "2020-06-17 15:31:11",
            "grant_unit": "7000",
            "grant_unit_short": "资金事业部|7000",
            "grant_way": "现金",
            "initiatorr": "张昕",
            "initiatorr_c": "",
            "into_accounts_caty": null,
            "into_accounts_desc": null,
            "into_accounts_short": null,
            "into_shoft": null,
            "money_b": "肆万元整",
            "money_center": "",
            "money_l": "40000",
            "promise_num": null,
            "purpose": "资金部5月代付李志刚取业务费40000元，现恒昌付资金（流水号600801、591417）",
            "real_time": "2020-06-17 15:27:43",
            "sap_back": "910000175010002020/910000030170002020",
            "sap_msg": "会计凭证创建成功",
            "sap_status": "S",
            "sap_time": "2020-06-17 15:31:07",
            "sap_user": "HC0158",
            "serial_num": "615501",
            "shift_accounts_caty": null,
            "shift_accounts_desc": null,
            "shift_accounts_short": null,
            "shift_short": "",
            "submitter": "张昕"
        },
        {
            "accoun": "张昕",
            "com_code": "7000",
            "com_code_short": "资金事业部|7000",
            "comment": "",
            "create_time": "2020-06-17",
            "exec_time": "2020-06-17 15:32:38",
            "grant_unit": "1000",
            "grant_unit_short": "恒昌建材|1000",
            "grant_way": "现金",
            "initiatorr": "李利涓",
            "initiatorr_c": "",
            "into_accounts_caty": null,
            "into_accounts_desc": null,
            "into_accounts_short": null,
            "into_shoft": null,
            "money_b": "壹佰万元整",
            "money_center": "",
            "money_l": "1000000",
            "promise_num": null,
            "purpose": "3月转给资金部19年4月收到巩义一建河东社区一标回款100万元整，系该公司欠我公司货款保证金，资金部退回，具体记账咨询冯志勇",
            "real_time": "2020-06-17 08:41:12",
            "sap_back": "910000030270002020/910000175110002020",
            "sap_msg": "会计凭证创建成功",
            "sap_status": "S",
            "sap_time": "2020-06-17 15:32:34",
            "sap_user": "HC0158",
            "serial_num": "615290",
            "shift_accounts_caty": null,
            "shift_accounts_desc": null,
            "shift_accounts_short": null,
            "shift_short": "",
            "submitter": "张昕"
        },
        {
            "accoun": "张昕",
            "com_code": "1010",
            "com_code_short": "伟治建材|1010",
            "comment": "",
            "create_time": "2020-06-05",
            "exec_time": "2020-06-05 17:15:04",
            "grant_unit": "7000",
            "grant_unit_short": "资金事业部|7000",
            "grant_way": "现金",
            "initiatorr": "张昕",
            "initiatorr_c": "",
            "into_accounts_caty": null,
            "into_accounts_desc": null,
            "into_accounts_short": null,
            "into_shoft": null,
            "money_b": "壹佰万元整",
            "money_center": "",
            "money_l": "1000000",
            "promise_num": null,
            "purpose": "伟治付资金部100万元",
            "real_time": "2020-06-05 17:13:53",
            "sap_back": "910000033810102020/910000028370002020",
            "sap_msg": "会计凭证创建成功",
            "sap_status": "S",
            "sap_time": "2020-06-05 17:14:56",
            "sap_user": "HC0158",
            "serial_num": "606010",
            "shift_accounts_caty": null,
            "shift_accounts_desc": null,
            "shift_accounts_short": null,
            "shift_short": "",
            "submitter": "张昕"
        },
        {
            "accoun": "郑会娟",
            "com_code": "2000",
            "com_code_short": "山立建材|2000",
            "comment": "",
            "create_time": "2020-05-31",
            "exec_time": "2020-06-01 18:09:13",
            "grant_unit": "5000",
            "grant_unit_short": "万昌运输|5000",
            "grant_way": "现金",
            "initiatorr": "李君毅",
            "initiatorr_c": "",
            "into_accounts_caty": null,
            "into_accounts_desc": null,
            "into_accounts_short": null,
            "into_shoft": null,
            "money_b": "壹佰伍拾柒万玖仟陆佰叁拾伍元壹角陆分",
            "money_center": "",
            "money_l": "1579635.16",
            "promise_num": null,
            "purpose": "山立付万昌5月运费",
            "real_time": "2020-06-01 18:04:54",
            "sap_back": "910000075820002020/910000267450002020",
            "sap_msg": "会计凭证创建成功",
            "sap_status": "S",
            "sap_time": "2020-06-01 18:09:06",
            "sap_user": "HC0131",
            "serial_num": "602785",
            "shift_accounts_caty": null,
            "shift_accounts_desc": null,
            "shift_accounts_short": null,
            "shift_short": "",
            "submitter": "郑会娟"
        },
        {
            "accoun": "郑会娟",
            "com_code": "1010",
            "com_code_short": "伟治建材|1010",
            "comment": "",
            "create_time": "2020-05-31",
            "exec_time": "2020-06-01 18:03:48",
            "grant_unit": "5000",
            "grant_unit_short": "万昌运输|5000",
            "grant_way": "现金",
            "initiatorr": "李君毅",
            "initiatorr_c": "",
            "into_accounts_caty": null,
            "into_accounts_desc": null,
            "into_accounts_short": null,
            "into_shoft": null,
            "money_b": "壹拾贰万伍仟柒佰伍拾柒元柒角捌分",
            "money_center": "",
            "money_l": "125757.78",
            "promise_num": null,
            "purpose": "伟治付万昌5月运费",
            "real_time": "2020-06-01 18:01:52",
            "sap_back": "910000033310102020/910000267350002020",
            "sap_msg": "会计凭证创建成功",
            "sap_status": "S",
            "sap_time": "2020-06-01 18:03:42",
            "sap_user": "HC0131",
            "serial_num": "602782",
            "shift_accounts_caty": null,
            "shift_accounts_desc": null,
            "shift_accounts_short": null,
            "shift_short": "",
            "submitter": "郑会娟"
        },
        {
            "accoun": "郑会娟",
            "com_code": "1000",
            "com_code_short": "恒昌建材|1000",
            "comment": "",
            "create_time": "2020-05-31",
            "exec_time": "2020-06-01 16:27:25",
            "grant_unit": "5000",
            "grant_unit_short": "万昌运输|5000",
            "grant_way": "现金",
            "initiatorr": "李君毅",
            "initiatorr_c": "",
            "into_accounts_caty": null,
            "into_accounts_desc": null,
            "into_accounts_short": null,
            "into_shoft": null,
            "money_b": "贰佰叁拾伍万叁仟肆佰玖拾陆元肆角玖分",
            "money_center": "",
            "money_l": "2353496.49",
            "promise_num": null,
            "purpose": "5月恒昌-万昌往来，恒昌付万昌",
            "real_time": "2020-06-01 16:25:35",
            "sap_back": "910000157210002020/910000267250002020",
            "sap_msg": "会计凭证创建成功",
            "sap_status": "S",
            "sap_time": "2020-06-01 16:27:18",
            "sap_user": "HC0131",
            "serial_num": "602673",
            "shift_accounts_caty": null,
            "shift_accounts_desc": null,
            "shift_accounts_short": null,
            "shift_short": "",
            "submitter": "郑会娟"
        },
        {
            "accoun": "郑会娟",
            "com_code": "1010",
            "com_code_short": "伟治建材|1010",
            "comment": "",
            "create_time": "2020-05-31",
            "exec_time": "2020-06-01 16:16:11",
            "grant_unit": "2000",
            "grant_unit_short": "山立建材|2000",
            "grant_way": "现金",
            "initiatorr": "郑会娟",
            "initiatorr_c": "",
            "into_accounts_caty": null,
            "into_accounts_desc": null,
            "into_accounts_short": null,
            "into_shoft": null,
            "money_b": "玖万捌仟伍佰壹拾贰元伍角壹分",
            "money_center": "",
            "money_l": "98512.51",
            "promise_num": null,
            "purpose": "山立收伟治",
            "real_time": "2020-06-01 16:14:18",
            "sap_back": "910000033210102020/910000075720002020",
            "sap_msg": "会计凭证创建成功",
            "sap_status": "S",
            "sap_time": "2020-06-01 16:16:05",
            "sap_user": "HC0131",
            "serial_num": "602668",
            "shift_accounts_caty": null,
            "shift_accounts_desc": null,
            "shift_accounts_short": null,
            "shift_short": "",
            "submitter": "郑会娟"
        },
        {
            "accoun": "郑会娟",
            "com_code": "1000",
            "com_code_short": "恒昌建材|1000",
            "comment": "",
            "create_time": "2020-05-31",
            "exec_time": "2020-06-01 16:12:51",
            "grant_unit": "1010",
            "grant_unit_short": "伟治建材|1010",
            "grant_way": "现金",
            "initiatorr": "郑会娟",
            "initiatorr_c": "",
            "into_accounts_caty": null,
            "into_accounts_desc": null,
            "into_accounts_short": null,
            "into_shoft": null,
            "money_b": "陆拾陆万伍仟捌佰陆拾柒元壹角",
            "money_center": "",
            "money_l": "665867.1",
            "promise_num": null,
            "purpose": "恒昌付伟治款",
            "real_time": "2020-06-01 16:11:08",
            "sap_back": "910000157110002020/910000033110102020",
            "sap_msg": "会计凭证创建成功",
            "sap_status": "S",
            "sap_time": "2020-06-01 16:12:45",
            "sap_user": "HC0131",
            "serial_num": "602649",
            "shift_accounts_caty": null,
            "shift_accounts_desc": null,
            "shift_accounts_short": null,
            "shift_short": "",
            "submitter": "郑会娟"
        },
        {
            "accoun": "连娟",
            "com_code": "3000",
            "com_code_short": "银河建筑|3000",
            "comment": "",
            "create_time": "2020-05-31",
            "exec_time": "2020-06-01 11:26:38",
            "grant_unit": "1020",
            "grant_unit_short": "恒昌松大站|1020",
            "grant_way": "现金",
            "initiatorr": "连娟",
            "initiatorr_c": "",
            "into_accounts_caty": null,
            "into_accounts_desc": null,
            "into_accounts_short": null,
            "into_shoft": null,
            "money_b": "肆仟壹佰元整",
            "money_center": "",
            "money_l": "4100",
            "promise_num": null,
            "purpose": "月底往来调账，1020公司收取3000公司4100元",
            "real_time": "2020-06-01 11:23:48",
            "sap_back": "910000018630002020/910000000110202020",
            "sap_msg": "会计凭证创建成功",
            "sap_status": "S",
            "sap_time": "2020-06-01 11:26:32",
            "sap_user": "HC0121",
            "serial_num": "602534",
            "shift_accounts_caty": null,
            "shift_accounts_desc": null,
            "shift_accounts_short": null,
            "shift_short": "",
            "submitter": "连娟"
        },
        {
            "accoun": "连娟",
            "com_code": "3000",
            "com_code_short": "银河建筑|3000",
            "comment": "",
            "create_time": "2020-05-31",
            "exec_time": "2020-06-01 11:16:22",
            "grant_unit": "1000",
            "grant_unit_short": "恒昌建材|1000",
            "grant_way": "现金",
            "initiatorr": "连娟",
            "initiatorr_c": "",
            "into_accounts_caty": null,
            "into_accounts_desc": null,
            "into_accounts_short": null,
            "into_shoft": null,
            "money_b": "玖万叁仟陆佰贰拾叁元叁角肆分",
            "money_center": "",
            "money_l": "93623.34",
            "promise_num": null,
            "purpose": "月底往来调账，1000公司收取3000公司93623.34元",
            "real_time": "2020-06-01 11:14:45",
            "sap_back": "910000018530002020/910000156910002020",
            "sap_msg": "会计凭证创建成功",
            "sap_status": "S",
            "sap_time": "2020-06-01 11:16:16",
            "sap_user": "HC0121",
            "serial_num": "602529",
            "shift_accounts_caty": null,
            "shift_accounts_desc": null,
            "shift_accounts_short": null,
            "shift_short": "",
            "submitter": "连娟"
        }
    ]
}