{
    "code": 0,
    "count":32,
    "data": [
        {
            "assist": "B1000055",
            "car_num": "2#卡特",
            "cardno": "1000111200000020068",
            "carid": "2#卡特钩机",
            "company": "5000|巩义市万昌运输有限公司",
            "cost_detail": "劳务成本-柴油-3070",
            "dtime": "2020-06-20 07:25:37",
            "empid": "B1000055",
            "gs_code": "5000",
            "id": 12982,
            "matid": "0#",
            "money": "1548.9100",
            "num": "347.2900",
            "obj_category": "内部订单",
            "price": "4.4600",
            "recorded_category": "30-劳务成本",
            "sap_back": "",
            "sap_money": "0",
            "sap_msg": "",
            "sap_msg_ht": null,
            "sap_msg_sell": "",
            "sap_status": "",
            "sap_status_ht": null,
            "sap_status_sell": "",
            "sap_time": null,
            "sap_user": "",
            "station_name": "恒昌公司加油车",
            "station_no": 1,
            "supplier": "110579|万昌加油机柴油消耗",
            "sync_time": "2020-06-20 07:36:04",
            "tally": "2241010000|其他应付款",
            "terminal": 3
        },
        {
            "assist": "A1000059",
            "car_num": "59",
            "cardno": "1000111200000020032",
            "carid": "豫AQ2276-59#",
            "company": "5000|巩义市万昌运输有限公司",
            "cost_detail": "劳务成本-柴油-3070",
            "dtime": "2020-06-20 06:59:02",
            "empid": "A1000059",
            "gs_code": "5000",
            "id": 12981,
            "matid": "0#",
            "money": "599.8100",
            "num": "136.0100",
            "obj_category": "内部订单",
            "price": "4.4100",
            "recorded_category": "30-劳务成本",
            "sap_back": "",
            "sap_money": "0",
            "sap_msg": "",
            "sap_msg_ht": null,
            "sap_msg_sell": "",
            "sap_status": "",
            "sap_status_ht": null,
            "sap_status_sell": "",
            "sap_time": null,
            "sap_user": "",
            "station_name": "恒昌公司加油车",
            "station_no": 1,
            "supplier": "110579|万昌加油机柴油消耗",
            "sync_time": "2020-06-20 07:04:04",
            "tally": "2241010000|其他应付款",
            "terminal": 2
        },
        {
            "assist": "C200002000",
            "car_num": "铲车",
            "cardno": "1000111200000020115",
            "carid": "山立铲车（破碎）",
            "company": "2000|河南省山立建材科技有限公司",
            "cost_detail": "制造费用-维修费-2020",
            "dtime": "2020-06-20 06:34:22",
            "empid": "",
            "gs_code": "2000",
            "id": 12980,
            "matid": "0#",
            "money": "940.8300",
            "num": "210.9500",
            "obj_category": "成本中心",
            "price": "4.4600",
            "recorded_category": "20-制造费用",
            "sap_back": "",
            "sap_money": "0",
            "sap_msg": "",
            "sap_msg_ht": null,
            "sap_msg_sell": "",
            "sap_status": "",
            "sap_status_ht": null,
            "sap_status_sell": "",
            "sap_time": null,
            "sap_user": "",
            "station_name": "恒昌公司加油车",
            "station_no": 1,
            "supplier": "5000|巩义市万昌运输有限公司",
            "sync_time": "2020-06-20 06:40:04",
            "tally": "2202000000|应付账款（通用）",
            "terminal": 3
        },
        {
            "assist": "A1000099",
            "car_num": "99",
            "cardno": "1000111200000020154",
            "carid": "豫A1176Q-99#",
            "company": "5000|巩义市万昌运输有限公司",
            "cost_detail": "劳务成本-柴油-3070",
            "dtime": "2020-06-20 06:13:34",
            "empid": "A1000099",
            "gs_code": "5000",
            "id": 12979,
            "matid": "0#",
            "money": "1084.9500",
            "num": "246.0200",
            "obj_category": "内部订单",
            "price": "4.4100",
            "recorded_category": "30-劳务成本",
            "sap_back": "",
            "sap_money": "0",
            "sap_msg": "",
            "sap_msg_ht": null,
            "sap_msg_sell": "",
            "sap_status": "",
            "sap_status_ht": null,
            "sap_status_sell": "",
            "sap_time": null,
            "sap_user": "",
            "station_name": "恒昌公司加油车",
            "station_no": 1,
            "supplier": "110579|万昌加油机柴油消耗",
            "sync_time": "2020-06-20 06:22:04",
            "tally": "2241010000|其他应付款",
            "terminal": 2
        },
        {
            "assist": "A1000109",
            "car_num": "108",
            "cardno": "1000111200000020130",
            "carid": "豫A2531E",
            "company": "5000|巩义市万昌运输有限公司",
            "cost_detail": "劳务成本-柴油-3070",
            "dtime": "2020-06-20 05:48:43",
            "empid": "A1000109",
            "gs_code": "5000",
            "id": 12978,
            "matid": "0#",
            "money": "1093.1900",
            "num": "245.1100",
            "obj_category": "内部订单",
            "price": "4.4600",
            "recorded_category": "30-劳务成本",
            "sap_back": "",
            "sap_money": "0",
            "sap_msg": "",
            "sap_msg_ht": null,
            "sap_msg_sell": "",
            "sap_status": "",
            "sap_status_ht": null,
            "sap_status_sell": "",
            "sap_time": null,
            "sap_user": "",
            "station_name": "恒昌公司加油车",
            "station_no": 1,
            "supplier": "110579|万昌加油机柴油消耗",
            "sync_time": "2020-06-20 05:56:03",
            "tally": "2241010000|其他应付款",
            "terminal": 3
        },
        {
            "assist": "C100002000",
            "car_num": "铲车1",
            "cardno": "1000111200000020096",
            "carid": "恒昌铲车",
            "company": "1000|河南省恒昌建材科技有限公司",
            "cost_detail": "制造费用-维修费-2020",
            "dtime": "2020-06-20 05:39:45",
            "empid": "恒昌建材",
            "gs_code": "1000",
            "id": 12977,
            "matid": "0#",
            "money": "1120.5800",
            "num": "254.1000",
            "obj_category": "成本中心",
            "price": "4.4100",
            "recorded_category": "20-制造费用",
            "sap_back": "",
            "sap_money": "0",
            "sap_msg": "",
            "sap_msg_ht": null,
            "sap_msg_sell": "",
            "sap_status": "",
            "sap_status_ht": null,
            "sap_status_sell": "",
            "sap_time": null,
            "sap_user": "",
            "station_name": "恒昌公司加油车",
            "station_no": 1,
            "supplier": "5000|巩义市万昌运输有限公司",
            "sync_time": "2020-06-20 05:48:04",
            "tally": "2202000000|应付账款（通用）",
            "terminal": 2
        },
        {
            "assist": "C200002000",
            "car_num": "铲车",
            "cardno": "1000111200000020115",
            "carid": "山立铲车（破碎）",
            "company": "2000|河南省山立建材科技有限公司",
            "cost_detail": "制造费用-维修费-2020",
            "dtime": "2020-06-20 05:40:17",
            "empid": "",
            "gs_code": "2000",
            "id": 12976,
            "matid": "0#",
            "money": "855.3300",
            "num": "191.7800",
            "obj_category": "成本中心",
            "price": "4.4600",
            "recorded_category": "20-制造费用",
            "sap_back": "",
            "sap_money": "0",
            "sap_msg": "",
            "sap_msg_ht": null,
            "sap_msg_sell": "",
            "sap_status": "",
            "sap_status_ht": null,
            "sap_status_sell": "",
            "sap_time": null,
            "sap_user": "",
            "station_name": "恒昌公司加油车",
            "station_no": 1,
            "supplier": "5000|巩义市万昌运输有限公司",
            "sync_time": "2020-06-20 05:48:04",
            "tally": "2202000000|应付账款（通用）",
            "terminal": 3
        },
        {
            "assist": "A1000065",
            "car_num": "65",
            "cardno": "1000111200000020037",
            "carid": "豫AQ2318-65#",
            "company": "5000|巩义市万昌运输有限公司",
            "cost_detail": "劳务成本-柴油-3070",
            "dtime": "2020-06-20 04:43:37",
            "empid": "A1000065",
            "gs_code": "5000",
            "id": 12975,
            "matid": "0#",
            "money": "523.1100",
            "num": "117.2900",
            "obj_category": "内部订单",
            "price": "4.4600",
            "recorded_category": "30-劳务成本",
            "sap_back": "",
            "sap_money": "0",
            "sap_msg": "",
            "sap_msg_ht": null,
            "sap_msg_sell": "",
            "sap_status": "",
            "sap_status_ht": null,
            "sap_status_sell": "",
            "sap_time": null,
            "sap_user": "",
            "station_name": "恒昌公司加油车",
            "station_no": 1,
            "supplier": "110579|万昌加油机柴油消耗",
            "sync_time": "2020-06-20 04:48:04",
            "tally": "2241010000|其他应付款",
            "terminal": 3
        },
        {
            "assist": "B1000035",
            "car_num": "豫A1997V",
            "cardno": "1000111200000020113",
            "carid": "豫A1997V",
            "company": "5000|巩义市万昌运输有限公司",
            "cost_detail": "劳务成本-柴油-3070",
            "dtime": "2020-06-20 04:16:23",
            "empid": "B1000035",
            "gs_code": "5000",
            "id": 12974,
            "matid": "0#",
            "money": "1120.1000",
            "num": "253.9900",
            "obj_category": "内部订单",
            "price": "4.4100",
            "recorded_category": "30-劳务成本",
            "sap_back": "",
            "sap_money": "0",
            "sap_msg": "",
            "sap_msg_ht": null,
            "sap_msg_sell": "",
            "sap_status": "",
            "sap_status_ht": null,
            "sap_status_sell": "",
            "sap_time": null,
            "sap_user": "",
            "station_name": "恒昌公司加油车",
            "station_no": 1,
            "supplier": "110579|万昌加油机柴油消耗",
            "sync_time": "2020-06-20 04:26:04",
            "tally": "2241010000|其他应付款",
            "terminal": 2
        },
        {
            "assist": "A1000068",
            "car_num": "68",
            "cardno": "1000111200000020039",
            "carid": "豫AQ2321-68#",
            "company": "5000|巩义市万昌运输有限公司",
            "cost_detail": "劳务成本-柴油-3070",
            "dtime": "2020-06-20 02:43:58",
            "empid": "A1000068",
            "gs_code": "5000",
            "id": 12973,
            "matid": "0#",
            "money": "305.9200",
            "num": "69.3700",
            "obj_category": "内部订单",
            "price": "4.4100",
            "recorded_category": "30-劳务成本",
            "sap_back": "",
            "sap_money": "0",
            "sap_msg": "",
            "sap_msg_ht": null,
            "sap_msg_sell": "",
            "sap_status": "",
            "sap_status_ht": null,
            "sap_status_sell": "",
            "sap_time": null,
            "sap_user": "",
            "station_name": "恒昌公司加油车",
            "station_no": 1,
            "supplier": "110579|万昌加油机柴油消耗",
            "sync_time": "2020-06-20 02:48:04",
            "tally": "2241010000|其他应付款",
            "terminal": 2
        }
    ]
}